pyprotondb/ProtonDBclient.py
pyprotondb/ProtonRequest.py
pyprotondb/ProtonResponse.py
pyprotondb/__init__.py
pyprotondb/connection.py
pyprotondb/protondbdriver.py
pyprotondb-0.1.0.dist-info/METADATA
pyprotondb-0.1.0.dist-info/WHEEL
pyprotondb-0.1.0.dist-info/top_level.txt
pyprotondb-0.1.0.dist-info/RECORD
