Metadata-Version: 2.4
Name: pyprotondb
Version: 0.1.0
Summary: A lightweight Python client for interacting with a ProtonDB-like server
Home-page: https://github.com/sarveshsarvs/ProtonDB/tree/master/Wrapper/pyproton
Author: Sarvesh J
Author-email: sarveshjrgar@gmail.com
Classifier: Programming Language :: Python :: 3
Classifier: Operating System :: OS Independent
Requires-Python: >=3.6
